zope.app.i18n-4.1.0-py3.8-nspkg.pth
zope/app/i18n/__init__.py
zope/app/i18n/configure.zcml
zope/app/i18n/filters.py
zope/app/i18n/interfaces.py
zope/app/i18n/messagecatalog.py
zope/app/i18n/translationdomain.py
zope/app/i18n/browser/__init__.py
zope/app/i18n/browser/configure.zcml
zope/app/i18n/browser/exportimport.pt
zope/app/i18n/browser/exportimport.py
zope/app/i18n/browser/i18n_domain.gif
zope/app/i18n/browser/synchronize.pt
zope/app/i18n/browser/synchronize.py
zope/app/i18n/browser/translate.pt
zope/app/i18n/browser/translate.py
zope/app/i18n/browser/translatemessage.pt
zope/app/i18n/browser/tests/__init__.py
zope/app/i18n/browser/tests/test_exportimport.py
zope/app/i18n/browser/tests/test_translate.py
zope/app/i18n/tests/__init__.py
zope/app/i18n/tests/configure.zcml
zope/app/i18n/tests/ftesting.zcml
zope/app/i18n/tests/test_configure.py
zope/app/i18n/tests/test_filters.py
zope/app/i18n/tests/test_messagecatalog.py
zope/app/i18n/tests/test_translationdomain.py
zope/app/i18n/xmlrpc/__init__.py
zope/app/i18n/xmlrpc/configure.zcml
zope/app/i18n/xmlrpc/methods.py
zope/app/i18n/xmlrpc/tests/__init__.py
zope/app/i18n/xmlrpc/tests/test_methods.py
zope.app.i18n-4.1.0.dist-info/LICENSE.txt
zope.app.i18n-4.1.0.dist-info/METADATA
zope.app.i18n-4.1.0.dist-info/WHEEL
zope.app.i18n-4.1.0.dist-info/namespace_packages.txt
zope.app.i18n-4.1.0.dist-info/top_level.txt
zope.app.i18n-4.1.0.dist-info/RECORD
