Metadata-Version: 2.1
Name: zope.app.i18n
Version: 4.1.0
Summary: Persistent translation domains and message catalogs
Home-page: http://github.com/zopefoundation/zope.app.i18n
Author: Zope Corporation and Contributors
Author-email: zope-dev@zope.org
License: ZPL 2.1
Keywords: zope3 i18n message factory
Platform: UNKNOWN
Classifier: Development Status :: 5 - Production/Stable
Classifier: Environment :: Web Environment
Classifier: Intended Audience :: Developers
Classifier: License :: OSI Approved :: Zope Public License
Classifier: Programming Language :: Python
Classifier: Programming Language :: Python :: 2
Classifier: Programming Language :: Python :: 2.7
Classifier: Programming Language :: Python :: 3
Classifier: Programming Language :: Python :: 3.5
Classifier: Programming Language :: Python :: 3.6
Classifier: Programming Language :: Python :: 3.7
Classifier: Programming Language :: Python :: Implementation :: CPython
Classifier: Programming Language :: Python :: Implementation :: PyPy
Classifier: Natural Language :: English
Classifier: Operating System :: OS Independent
Classifier: Topic :: Internet :: WWW/HTTP
Classifier: Framework :: Zope :: 3
Requires-Dist: BTrees (>=4.4.1)
Requires-Dist: persistent (>=4.2.4)
Requires-Dist: setuptools
Requires-Dist: zope.app.publisher (>=4.0.0)
Requires-Dist: zope.component (>=4.3.0)
Requires-Dist: zope.configuration
Requires-Dist: zope.container (>=4.1.0)
Requires-Dist: zope.i18n (!=4.5.*,!=4.6.*,>=4.2.0)
Requires-Dist: zope.i18nmessageid (>=4.1.0)
Requires-Dist: zope.interface (>=3.8.0)
Requires-Dist: zope.publisher (>=4.3.2)
Requires-Dist: zope.security
Provides-Extra: test
Requires-Dist: zope.app.component ; extra == 'test'
Requires-Dist: zope.testing ; extra == 'test'
Requires-Dist: zope.testrunner ; extra == 'test'
